src/Cmd.py
src/__init__.py
src/database/DbTables.py
src/database/__init__.py
src/service/ComplexFeatureService.py
src/service/FeatureStoreService.py
src/service/SimpleFeatureService.py
src/service/__init__.py
src/utils/__init__.py
src/utils/multi_melt.py
src/utils/process_logging.py
tests/UnitTest.py
tests/__init__.py
Hopsworks_Integration-0.0.2.dist-info/LICENSE
Hopsworks_Integration-0.0.2.dist-info/METADATA
Hopsworks_Integration-0.0.2.dist-info/WHEEL
Hopsworks_Integration-0.0.2.dist-info/top_level.txt
Hopsworks_Integration-0.0.2.dist-info/RECORD
