Metadata-Version: 2.1
Name: Hopsworks-Integration
Version: 0.0.2
Summary: A python package that exposes functions to interact with the Hopsworks feature store
Home-page: https://github.com/muneebsmh/hopsworks-integrations.git
Author: Syed Muneeb Hussain
Author-email: muneebhussain94@gmail.com
License: UNKNOWN
Platform: UNKNOWN
Classifier: Programming Language :: Python :: 3
Classifier: License :: OSI Approved :: MIT License
Classifier: Operating System :: OS Independent
Requires-Python: >=3.7,<3.10
License-File: LICENSE
Requires-Dist: hopsworks (==3.0.3)
Requires-Dist: pandas
Requires-Dist: SQLAlchemy
Requires-Dist: pytest
